scrapy_oxylabs_proxy/__init__.py
scrapy_oxylabs_proxy/middleware.py
scrapy_oxylabs_proxy-0.1.0.dist-info/licenses/LICENSE
scrapy_oxylabs_proxy-0.1.0.dist-info/METADATA
scrapy_oxylabs_proxy-0.1.0.dist-info/WHEEL
scrapy_oxylabs_proxy-0.1.0.dist-info/top_level.txt
scrapy_oxylabs_proxy-0.1.0.dist-info/RECORD
