Metadata-Version: 2.4
Name: scrapy-oxylabs-proxy
Version: 0.1.0
Summary: Scrapy middleware for Oxylabs Web Scraper API in proxy mode
Author: Abdul Nazar
Classifier: Programming Language :: Python :: 3
Classifier: Framework :: Scrapy
Classifier: License :: OSI Approved :: MIT License
Classifier: Operating System :: OS Independent
Requires-Python: >=3.6
License-File: LICENSE
Dynamic: author
Dynamic: classifier
Dynamic: description
Dynamic: description-content-type
Dynamic: license-file
Dynamic: requires-python
Dynamic: summary
